{
  "type": "minecraft:entity",
  "pools": [
    {
      "rolls": 2,
      "entries": [
        {
          "entryName": "coal",
          "type": "minecraft:item",
          "name": "minecraft:coal",
          "functions": [
            {
              "function": "minecraft:set_count",
              "count": {
                "min": 1.0,
                "max": 5.0,
                "type": "minecraft:uniform"
              }
            }
          ]          
        },      
        {
          "entryName": "fire_charge",
          "type": "minecraft:item",
          "name": "minecraft:fire_charge",
          "functions": [
            {
              "function": "minecraft:set_count",
              "count": {
                "min": 0.0,
                "max": 2.0,
                "type": "minecraft:uniform"
              }
            }
          ]          
        },
        {
          "entryName": "gunpowder",
          "type": "minecraft:item",
          "name": "minecraft:gunpowder",
          "functions": [
            {
              "function": "minecraft:set_count",
              "count": {
                "min": 1.0,
                "max": 3.0,
                "type": "minecraft:uniform"
              }
            }
          ]          
        }
      ]
    },
    {
      "rolls": 1,
      "entries": [
        {
          "entryName": "diamond",
          "type": "minecraft:item",
          "name": "minecraft:diamond",
          "functions": [
            {
              "function": "minecraft:set_count",
              "count": {
                "min": 1.0,
                "max": 3.0,
                "type": "minecraft:uniform"
              }
            }
          ]          
        },
        {
          "entryName": "emerald",
          "type": "minecraft:item",
          "name": "minecraft:emerald",
          "functions": [
            {
              "function": "minecraft:set_count",
              "count": {
                "min": 1.0,
                "max": 3.0,
                "type": "minecraft:uniform"
              }
            }
          ]          
        }
      ]
    }
  ]
}